{"controlled_route_contrasts":[{"baseline_route_id":"A00_tiny_direct","candidate_route_id":"A01_tiny_bm25","gpu_joules_difference":{"clusters":120,"high":108.98896094998203,"low":96.65827359713379,"mean":102.96914618265455,"replicates":10000},"success_difference":{"clusters":120,"high":-0.06666666666666667,"low":-0.18333333333333332,"mean":-0.125,"replicates":10000}},{"baseline_route_id":"A00_tiny_direct","candidate_route_id":"A02_tiny_dense","gpu_joules_difference":{"clusters":120,"high":101.27199017227686,"low":89.80410340011736,"mean":95.69525323500648,"replicates":10000},"success_difference":{"clusters":120,"high":-0.06666666666666667,"low":-0.18333333333333332,"mean":-0.125,"replicates":10000}},{"baseline_route_id":"A00_tiny_direct","candidate_route_id":"A03_tiny_hybrid","gpu_joules_difference":{"clusters":120,"high":94.20426872935627,"low":82.51745341251754,"mean":88.44180447522305,"replicates":10000},"success_difference":{"clusters":120,"high":-0.06666666666666667,"low":-0.18333333333333332,"mean":-0.125,"replicates":10000}},{"baseline_route_id":"A00_tiny_direct","candidate_route_id":"A08_tiny_memory_flat","gpu_joules_difference":{"clusters":120,"high":98.95041817641601,"low":89.43526375366272,"mean":94.2468927991135,"replicates":10000},"success_difference":{"clusters":120,"high":-0.06666666666666667,"low":-0.18333333333333332,"mean":-0.125,"replicates":10000}},{"baseline_route_id":"A00_tiny_direct","candidate_route_id":"A09_tiny_memory_hier","gpu_joules_difference":{"clusters":120,"high":120.55501920355609,"low":110.5006587581026,"mean":115.60384640284042,"replicates":10000},"success_difference":{"clusters":120,"high":-0.06666666666666667,"low":-0.18333333333333332,"mean":-0.125,"replicates":10000}},{"baseline_route_id":"A00_tiny_direct","candidate_route_id":"A10_tiny_memory_graph","gpu_joules_difference":{"clusters":120,"high":121.27923716861588,"low":111.89997213333494,"mean":116.77332947456748,"replicates":10000},"success_difference":{"clusters":120,"high":-0.06666666666666667,"low":-0.18333333333333332,"mean":-0.125,"replicates":10000}},{"baseline_route_id":"A00_tiny_direct","candidate_route_id":"A04_small_direct","gpu_joules_difference":{"clusters":120,"high":205.39652946873017,"low":199.0903692895098,"mean":202.2613016412211,"replicates":10000},"success_difference":{"clusters":120,"high":-0.06666666666666667,"low":-0.18333333333333332,"mean":-0.125,"replicates":10000}}],"scenario_class_statistics":[{"abstention_rate":1.0,"energy_coverage":1.0,"execution_failure_rate":0.0,"mean_gpu_joules":42.75103262784699,"queries":15,"route_id":"A00_tiny_direct","success_rate":0.0,"task_type":"authority_conflict"},{"abstention_rate":0.0,"energy_coverage":1.0,"execution_failure_rate":0.0,"mean_gpu_joules":162.16809421037033,"queries":15,"route_id":"A01_tiny_bm25","success_rate":0.0,"task_type":"authority_conflict"},{"abstention_rate":0.0,"energy_coverage":1.0,"execution_failure_rate":0.0,"mean_gpu_joules":153.77142262227184,"queries":15,"route_id":"A02_tiny_dense","success_rate":0.0,"task_type":"authority_conflict"},{"abstention_rate":0.0,"energy_coverage":1.0,"execution_failure_rate":0.0,"mean_gpu_joules":151.82092577426778,"queries":15,"route_id":"A03_tiny_hybrid","success_rate":0.0,"task_type":"authority_conflict"},{"abstention_rate":0.0,"energy_coverage":1.0,"execution_failure_rate":0.0,"mean_gpu_joules":260.3335614507853,"queries":15,"route_id":"A04_small_direct","success_rate":0.0,"task_type":"authority_conflict"},{"abstention_rate":0.7333333333333333,"energy_coverage":1.0,"execution_failure_rate":0.0,"mean_gpu_joules":104.14444673987624,"queries":15,"route_id":"A08_tiny_memory_flat","success_rate":0.0,"task_type":"authority_conflict"},{"abstention_rate":0.8666666666666667,"energy_coverage":1.0,"execution_failure_rate":0.0,"mean_gpu_joules":109.80894831785669,"queries":15,"route_id":"A09_tiny_memory_hier","success_rate":0.0,"task_type":"authority_conflict"},{"abstention_rate":0.8,"energy_coverage":1.0,"execution_failure_rate":0.0,"mean_gpu_joules":116.61787067576567,"queries":15,"route_id":"A10_tiny_memory_graph","success_rate":0.0,"task_type":"authority_conflict"},{"abstention_rate":0.0,"energy_coverage":1.0,"execution_failure_rate":0.0,"mean_gpu_joules":259.4632695823213,"queries":15,"route_id":"A12_small_hybrid_both","success_rate":0.0,"task_type":"authority_conflict"},{"abstention_rate":1.0,"energy_coverage":1.0,"execution_failure_rate":0.0,"mean_gpu_joules":261.2606316930786,"queries":15,"route_id":"A13_small_hybrid_verified","success_rate":0.0,"task_type":"authority_conflict"},{"abstention_rate":0.4,"energy_coverage":1.0,"execution_failure_rate":0.0,"mean_gpu_joules":282.8984779930436,"queries":15,"route_id":"A14_upper_hybrid_verified","success_rate":0.4,"task_type":"authority_conflict"},{"abstention_rate":1.0,"energy_coverage":1.0,"execution_failure_rate":0.0,"mean_gpu_joules":180.1887563791907,"queries":15,"route_id":"M16_tiny_grounded_verified","success_rate":0.0,"task_type":"authority_conflict"},{"abstention_rate":1.0,"energy_coverage":1.0,"execution_failure_rate":0.0,"mean_gpu_joules":43.92521095946732,"queries":15,"route_id":"M17_granite_direct","success_rate":0.0,"task_type":"authority_conflict"},{"abstention_rate":0.0,"energy_coverage":1.0,"execution_failure_rate":0.0,"mean_gpu_joules":168.85840412978663,"queries":15,"route_id":"M18_granite_grounded_verified","success_rate":0.4,"task_type":"authority_conflict"},{"abstention_rate":0.0,"energy_coverage":1.0,"execution_failure_rate":0.0,"mean_gpu_joules":88.40860302789913,"queries":15,"route_id":"M19_peer_direct","success_rate":0.0,"task_type":"authority_conflict"},{"abstention_rate":0.5333333333333333,"energy_coverage":1.0,"execution_failure_rate":0.0,"mean_gpu_joules":149.39430525482646,"queries":15,"route_id":"M20_peer_grounded_verified","success_rate":0.3333333333333333,"task_type":"authority_conflict"},{"abstention_rate":1.0,"energy_coverage":1.0,"execution_failure_rate":0.0,"mean_gpu_joules":83.51103128238228,"queries":15,"route_id":"M21_upper_direct","success_rate":0.0,"task_type":"authority_conflict"},{"abstention_rate":0.3333333333333333,"energy_coverage":1.0,"execution_failure_rate":0.0,"mean_gpu_joules":76.9308366589898,"queries":15,"route_id":"A00_tiny_direct","success_rate":0.0,"task_type":"deleted_or_missing"},{"abstention_rate":0.0,"energy_coverage":1.0,"execution_failure_rate":0.0,"mean_gpu_joules":173.39972113984598,"queries":15,"route_id":"A01_tiny_bm25","success_rate":0.0,"task_type":"deleted_or_missing"},{"abstention_rate":0.0,"energy_coverage":1.0,"execution_failure_rate":0.0,"mean_gpu_joules":168.17323902947012,"queries":15,"route_id":"A02_tiny_dense","success_rate":0.0,"task_type":"deleted_or_missing"},{"abstention_rate":0.0,"energy_coverage":1.0,"execution_failure_rate":0.0,"mean_gpu_joules":161.26237945710358,"queries":15,"route_id":"A03_tiny_hybrid","success_rate":0.0,"task_type":"deleted_or_missing"},{"abstention_rate":0.0,"energy_coverage":1.0,"execution_failure_rate":0.0,"mean_gpu_joules":257.2293739122908,"queries":15,"route_id":"A04_small_direct","success_rate":0.0,"task_type":"deleted_or_missing"},{"abstention_rate":0.0,"energy_coverage":1.0,"execution_failure_rate":0.0,"mean_gpu_joules":165.73916271513824,"queries":15,"route_id":"A08_tiny_memory_flat","success_rate":0.0,"task_type":"deleted_or_missing"},{"abstention_rate":0.0,"energy_coverage":1.0,"execution_failure_rate":0.0,"mean_gpu_joules":187.06589607290223,"queries":15,"route_id":"A09_tiny_memory_hier","success_rate":0.0,"task_type":"deleted_or_missing"},{"abstention_rate":0.0,"energy_coverage":1.0,"execution_failure_rate":0.0,"mean_gpu_joules":188.4209047849837,"queries":15,"route_id":"A10_tiny_memory_graph","success_rate":0.0,"task_type":"deleted_or_missing"},{"abstention_rate":0.0,"energy_coverage":1.0,"execution_failure_rate":0.0,"mean_gpu_joules":260.2912601280209,"queries":15,"route_id":"A12_small_hybrid_both","success_rate":0.0,"task_type":"deleted_or_missing"},{"abstention_rate":1.0,"energy_coverage":1.0,"execution_failure_rate":0.0,"mean_gpu_joules":259.94045407098065,"queries":15,"route_id":"A13_small_hybrid_verified","success_rate":0.0,"task_type":"deleted_or_missing"},{"abstention_rate":0.4,"energy_coverage":1.0,"execution_failure_rate":0.0,"mean_gpu_joules":296.94271773637377,"queries":15,"route_id":"A14_upper_hybrid_verified","success_rate":0.0,"task_type":"deleted_or_missing"},{"abstention_rate":1.0,"energy_coverage":1.0,"execution_failure_rate":0.0,"mean_gpu_joules":218.98213861227188,"queries":15,"route_id":"M16_tiny_grounded_verified","success_rate":0.0,"task_type":"deleted_or_missing"},{"abstention_rate":1.0,"energy_coverage":1.0,"execution_failure_rate":0.0,"mean_gpu_joules":60.823660576634786,"queries":15,"route_id":"M17_granite_direct","success_rate":1.0,"task_type":"deleted_or_missing"},{"abstention_rate":0.0,"energy_coverage":1.0,"execution_failure_rate":0.0,"mean_gpu_joules":188.946754521238,"queries":15,"route_id":"M18_granite_grounded_verified","success_rate":0.0,"task_type":"deleted_or_missing"},{"abstention_rate":1.0,"energy_coverage":1.0,"execution_failure_rate":0.0,"mean_gpu_joules":116.3947956095169,"queries":15,"route_id":"M19_peer_direct","success_rate":1.0,"task_type":"deleted_or_missing"},{"abstention_rate":0.13333333333333333,"energy_coverage":1.0,"execution_failure_rate":0.0,"mean_gpu_joules":149.05284879693446,"queries":15,"route_id":"M20_peer_grounded_verified","success_rate":0.13333333333333333,"task_type":"deleted_or_missing"},{"abstention_rate":1.0,"energy_coverage":1.0,"execution_failure_rate":0.0,"mean_gpu_joules":84.14299029312802,"queries":15,"route_id":"M21_upper_direct","success_rate":1.0,"task_type":"deleted_or_missing"},{"abstention_rate":0.26666666666666666,"energy_coverage":1.0,"execution_failure_rate":0.0,"mean_gpu_joules":53.905992214957855,"queries":15,"route_id":"A00_tiny_direct","success_rate":0.0,"task_type":"knowledge_memory"},{"abstention_rate":0.13333333333333333,"energy_coverage":1.0,"execution_failure_rate":0.0,"mean_gpu_joules":177.82212097917096,"queries":15,"route_id":"A01_tiny_bm25","success_rate":0.0,"task_type":"knowledge_memory"},{"abstention_rate":0.0,"energy_coverage":1.0,"execution_failure_rate":0.0,"mean_gpu_joules":166.22749711710597,"queries":15,"route_id":"A02_tiny_dense","success_rate":0.0,"task_type":"knowledge_memory"},{"abstention_rate":0.06666666666666667,"energy_coverage":1.0,"execution_failure_rate":0.0,"mean_gpu_joules":156.06818118519556,"queries":15,"route_id":"A03_tiny_hybrid","success_rate":0.0,"task_type":"knowledge_memory"},{"abstention_rate":0.0,"energy_coverage":1.0,"execution_failure_rate":0.0,"mean_gpu_joules":258.0927344454541,"queries":15,"route_id":"A04_small_direct","success_rate":0.0,"task_type":"knowledge_memory"},{"abstention_rate":0.0,"energy_coverage":1.0,"execution_failure_rate":0.0,"mean_gpu_joules":154.86512432282478,"queries":15,"route_id":"A08_tiny_memory_flat","success_rate":0.0,"task_type":"knowledge_memory"},{"abstention_rate":0.0,"energy_coverage":1.0,"execution_failure_rate":0.0,"mean_gpu_joules":180.21565116311618,"queries":15,"route_id":"A09_tiny_memory_hier","success_rate":0.0,"task_type":"knowledge_memory"},{"abstention_rate":0.0,"energy_coverage":1.0,"execution_failure_rate":0.0,"mean_gpu_joules":181.7023536248089,"queries":15,"route_id":"A10_tiny_memory_graph","success_rate":0.0,"task_type":"knowledge_memory"},{"abstention_rate":0.0,"energy_coverage":1.0,"execution_failure_rate":0.0,"mean_gpu_joules":258.3566446913967,"queries":15,"route_id":"A12_small_hybrid_both","success_rate":0.0,"task_type":"knowledge_memory"},{"abstention_rate":1.0,"energy_coverage":1.0,"execution_failure_rate":0.0,"mean_gpu_joules":261.16541383560633,"queries":15,"route_id":"A13_small_hybrid_verified","success_rate":0.0,"task_type":"knowledge_memory"},{"abstention_rate":0.4666666666666667,"energy_coverage":1.0,"execution_failure_rate":0.0,"mean_gpu_joules":331.10801852784846,"queries":15,"route_id":"A14_upper_hybrid_verified","success_rate":0.13333333333333333,"task_type":"knowledge_memory"},{"abstention_rate":1.0,"energy_coverage":1.0,"execution_failure_rate":0.0,"mean_gpu_joules":220.02629655163668,"queries":15,"route_id":"M16_tiny_grounded_verified","success_rate":0.0,"task_type":"knowledge_memory"},{"abstention_rate":1.0,"energy_coverage":1.0,"execution_failure_rate":0.0,"mean_gpu_joules":142.22348153414796,"queries":15,"route_id":"M17_granite_direct","success_rate":0.0,"task_type":"knowledge_memory"},{"abstention_rate":0.3333333333333333,"energy_coverage":1.0,"execution_failure_rate":0.0,"mean_gpu_joules":266.33680512074676,"queries":15,"route_id":"M18_granite_grounded_verified","success_rate":0.2,"task_type":"knowledge_memory"},{"abstention_rate":0.4666666666666667,"energy_coverage":1.0,"execution_failure_rate":0.0,"mean_gpu_joules":132.79485855854816,"queries":15,"route_id":"M19_peer_direct","success_rate":0.0,"task_type":"knowledge_memory"},{"abstention_rate":0.06666666666666667,"energy_coverage":1.0,"execution_failure_rate":0.0,"mean_gpu_joules":177.01297811142086,"queries":15,"route_id":"M20_peer_grounded_verified","success_rate":0.13333333333333333,"task_type":"knowledge_memory"},{"abstention_rate":1.0,"energy_coverage":1.0,"execution_failure_rate":0.0,"mean_gpu_joules":82.24980419437983,"queries":15,"route_id":"M21_upper_direct","success_rate":0.0,"task_type":"knowledge_memory"},{"abstention_rate":0.0,"energy_coverage":1.0,"execution_failure_rate":0.0,"mean_gpu_joules":45.44350391969525,"queries":15,"route_id":"A00_tiny_direct","success_rate":0.0,"task_type":"knowledge_only"},{"abstention_rate":0.26666666666666666,"energy_coverage":1.0,"execution_failure_rate":0.0,"mean_gpu_joules":164.45658187355878,"queries":15,"route_id":"A01_tiny_bm25","success_rate":0.0,"task_type":"knowledge_only"},{"abstention_rate":0.0,"energy_coverage":1.0,"execution_failure_rate":0.0,"mean_gpu_joules":148.20026824249177,"queries":15,"route_id":"A02_tiny_dense","success_rate":0.0,"task_type":"knowledge_only"},{"abstention_rate":0.0,"energy_coverage":1.0,"execution_failure_rate":0.0,"mean_gpu_joules":150.884456164918,"queries":15,"route_id":"A03_tiny_hybrid","success_rate":0.0,"task_type":"knowledge_only"},{"abstention_rate":0.0,"energy_coverage":1.0,"execution_failure_rate":0.0,"mean_gpu_joules":252.77144808068536,"queries":15,"route_id":"A04_small_direct","success_rate":0.0,"task_type":"knowledge_only"},{"abstention_rate":0.0,"energy_coverage":1.0,"execution_failure_rate":0.0,"mean_gpu_joules":152.75488146475902,"queries":15,"route_id":"A08_tiny_memory_flat","success_rate":0.0,"task_type":"knowledge_only"},{"abstention_rate":0.0,"energy_coverage":1.0,"execution_failure_rate":0.0,"mean_gpu_joules":171.22607994012571,"queries":15,"route_id":"A09_tiny_memory_hier","success_rate":0.0,"task_type":"knowledge_only"},{"abstention_rate":0.0,"energy_coverage":1.0,"execution_failure_rate":0.0,"mean_gpu_joules":169.19020877539648,"queries":15,"route_id":"A10_tiny_memory_graph","success_rate":0.0,"task_type":"knowledge_only"},{"abstention_rate":0.0,"energy_coverage":1.0,"execution_failure_rate":0.0,"mean_gpu_joules":256.4987512547478,"queries":15,"route_id":"A12_small_hybrid_both","success_rate":0.0,"task_type":"knowledge_only"},{"abstention_rate":1.0,"energy_coverage":1.0,"execution_failure_rate":0.0,"mean_gpu_joules":260.54881917900815,"queries":15,"route_id":"A13_small_hybrid_verified","success_rate":0.0,"task_type":"knowledge_only"},{"abstention_rate":0.06666666666666667,"energy_coverage":1.0,"execution_failure_rate":0.0,"mean_gpu_joules":230.42579735061386,"queries":15,"route_id":"A14_upper_hybrid_verified","success_rate":0.9333333333333333,"task_type":"knowledge_only"},{"abstention_rate":1.0,"energy_coverage":1.0,"execution_failure_rate":0.0,"mean_gpu_joules":213.73150844530912,"queries":15,"route_id":"M16_tiny_grounded_verified","success_rate":0.0,"task_type":"knowledge_only"},{"abstention_rate":1.0,"energy_coverage":1.0,"execution_failure_rate":0.0,"mean_gpu_joules":28.630518113784444,"queries":15,"route_id":"M17_granite_direct","success_rate":0.0,"task_type":"knowledge_only"},{"abstention_rate":0.06666666666666667,"energy_coverage":1.0,"execution_failure_rate":0.0,"mean_gpu_joules":164.08754066796646,"queries":15,"route_id":"M18_granite_grounded_verified","success_rate":0.9333333333333333,"task_type":"knowledge_only"},{"abstention_rate":0.8666666666666667,"energy_coverage":1.0,"execution_failure_rate":0.0,"mean_gpu_joules":78.86835597072236,"queries":15,"route_id":"M19_peer_direct","success_rate":0.0,"task_type":"knowledge_only"},{"abstention_rate":0.7333333333333333,"energy_coverage":1.0,"execution_failure_rate":0.0,"mean_gpu_joules":145.89833154579898,"queries":15,"route_id":"M20_peer_grounded_verified","success_rate":0.2,"task_type":"knowledge_only"},{"abstention_rate":1.0,"energy_coverage":1.0,"execution_failure_rate":0.0,"mean_gpu_joules":82.02277302102699,"queries":15,"route_id":"M21_upper_direct","success_rate":0.0,"task_type":"knowledge_only"},{"abstention_rate":0.8666666666666667,"energy_coverage":1.0,"execution_failure_rate":0.0,"mean_gpu_joules":56.42004409086118,"queries":15,"route_id":"A00_tiny_direct","success_rate":0.0,"task_type":"memory_only"},{"abstention_rate":0.6666666666666666,"energy_coverage":1.0,"execution_failure_rate":0.0,"mean_gpu_joules":118.8987295240299,"queries":15,"route_id":"A01_tiny_bm25","success_rate":0.0,"task_type":"memory_only"},{"abstention_rate":0.8666666666666667,"energy_coverage":1.0,"execution_failure_rate":0.0,"mean_gpu_joules":95.39648360498137,"queries":15,"route_id":"A02_tiny_dense","success_rate":0.0,"task_type":"memory_only"},{"abstention_rate":1.0,"energy_coverage":1.0,"execution_failure_rate":0.0,"mean_gpu_joules":88.85687402084582,"queries":15,"route_id":"A03_tiny_hybrid","success_rate":0.0,"task_type":"memory_only"},{"abstention_rate":0.0,"energy_coverage":1.0,"execution_failure_rate":0.0,"mean_gpu_joules":256.183157455725,"queries":15,"route_id":"A04_small_direct","success_rate":0.0,"task_type":"memory_only"},{"abstention_rate":0.0,"energy_coverage":1.0,"execution_failure_rate":0.0,"mean_gpu_joules":143.93484116884255,"queries":15,"route_id":"A08_tiny_memory_flat","success_rate":0.0,"task_type":"memory_only"},{"abstention_rate":0.0,"energy_coverage":1.0,"execution_failure_rate":0.0,"mean_gpu_joules":167.718078586009,"queries":15,"route_id":"A09_tiny_memory_hier","success_rate":0.0,"task_type":"memory_only"},{"abstention_rate":0.0,"energy_coverage":1.0,"execution_failure_rate":0.0,"mean_gpu_joules":169.5178117842064,"queries":15,"route_id":"A10_tiny_memory_graph","success_rate":0.0,"task_type":"memory_only"},{"abstention_rate":0.0,"energy_coverage":1.0,"execution_failure_rate":0.0,"mean_gpu_joules":258.34770143700115,"queries":15,"route_id":"A12_small_hybrid_both","success_rate":0.0,"task_type":"memory_only"},{"abstention_rate":1.0,"energy_coverage":1.0,"execution_failure_rate":0.0,"mean_gpu_joules":260.37624659971914,"queries":15,"route_id":"A13_small_hybrid_verified","success_rate":0.0,"task_type":"memory_only"},{"abstention_rate":0.2,"energy_coverage":1.0,"execution_failure_rate":0.0,"mean_gpu_joules":231.02794765851576,"queries":15,"route_id":"A14_upper_hybrid_verified","success_rate":0.6666666666666666,"task_type":"memory_only"},{"abstention_rate":0.8666666666666667,"energy_coverage":1.0,"execution_failure_rate":0.0,"mean_gpu_joules":195.93592164245567,"queries":15,"route_id":"M16_tiny_grounded_verified","success_rate":0.0,"task_type":"memory_only"},{"abstention_rate":1.0,"energy_coverage":1.0,"execution_failure_rate":0.0,"mean_gpu_joules":28.487366063797708,"queries":15,"route_id":"M17_granite_direct","success_rate":0.0,"task_type":"memory_only"},{"abstention_rate":0.0,"energy_coverage":1.0,"execution_failure_rate":0.0,"mean_gpu_joules":160.45617011942286,"queries":15,"route_id":"M18_granite_grounded_verified","success_rate":1.0,"task_type":"memory_only"},{"abstention_rate":1.0,"energy_coverage":1.0,"execution_failure_rate":0.0,"mean_gpu_joules":115.77123579872855,"queries":15,"route_id":"M19_peer_direct","success_rate":0.0,"task_type":"memory_only"},{"abstention_rate":0.0,"energy_coverage":1.0,"execution_failure_rate":0.0,"mean_gpu_joules":131.9971544734564,"queries":15,"route_id":"M20_peer_grounded_verified","success_rate":1.0,"task_type":"memory_only"},{"abstention_rate":1.0,"energy_coverage":1.0,"execution_failure_rate":0.0,"mean_gpu_joules":81.25822543633966,"queries":15,"route_id":"M21_upper_direct","success_rate":0.0,"task_type":"memory_only"},{"abstention_rate":0.0,"energy_coverage":1.0,"execution_failure_rate":0.0,"mean_gpu_joules":57.483896064977635,"queries":15,"route_id":"A00_tiny_direct","success_rate":0.0,"task_type":"multi_hop"},{"abstention_rate":0.06666666666666667,"energy_coverage":1.0,"execution_failure_rate":0.0,"mean_gpu_joules":158.03742996131916,"queries":15,"route_id":"A01_tiny_bm25","success_rate":0.0,"task_type":"multi_hop"},{"abstention_rate":0.0,"energy_coverage":1.0,"execution_failure_rate":0.0,"mean_gpu_joules":164.76450648778007,"queries":15,"route_id":"A02_tiny_dense","success_rate":0.0,"task_type":"multi_hop"},{"abstention_rate":0.13333333333333333,"energy_coverage":1.0,"execution_failure_rate":0.0,"mean_gpu_joules":141.51253422318987,"queries":15,"route_id":"A03_tiny_hybrid","success_rate":0.0,"task_type":"multi_hop"},{"abstention_rate":0.0,"energy_coverage":1.0,"execution_failure_rate":0.0,"mean_gpu_joules":259.44164523312503,"queries":15,"route_id":"A04_small_direct","success_rate":0.0,"task_type":"multi_hop"},{"abstention_rate":0.0,"energy_coverage":1.0,"execution_failure_rate":0.0,"mean_gpu_joules":151.0342137744032,"queries":15,"route_id":"A08_tiny_memory_flat","success_rate":0.0,"task_type":"multi_hop"},{"abstention_rate":0.0,"energy_coverage":1.0,"execution_failure_rate":0.0,"mean_gpu_joules":177.5626684396376,"queries":15,"route_id":"A09_tiny_memory_hier","success_rate":0.0,"task_type":"multi_hop"},{"abstention_rate":0.0,"energy_coverage":1.0,"execution_failure_rate":0.0,"mean_gpu_joules":177.14229602594898,"queries":15,"route_id":"A10_tiny_memory_graph","success_rate":0.0,"task_type":"multi_hop"},{"abstention_rate":0.0,"energy_coverage":1.0,"execution_failure_rate":0.0,"mean_gpu_joules":259.1941785933117,"queries":15,"route_id":"A12_small_hybrid_both","success_rate":0.0,"task_type":"multi_hop"},{"abstention_rate":1.0,"energy_coverage":1.0,"execution_failure_rate":0.0,"mean_gpu_joules":260.46817361918,"queries":15,"route_id":"A13_small_hybrid_verified","success_rate":0.0,"task_type":"multi_hop"},{"abstention_rate":0.26666666666666666,"energy_coverage":1.0,"execution_failure_rate":0.0,"mean_gpu_joules":322.45188480040645,"queries":15,"route_id":"A14_upper_hybrid_verified","success_rate":0.26666666666666666,"task_type":"multi_hop"},{"abstention_rate":1.0,"energy_coverage":1.0,"execution_failure_rate":0.0,"mean_gpu_joules":199.9296032353049,"queries":15,"route_id":"M16_tiny_grounded_verified","success_rate":0.0,"task_type":"multi_hop"},{"abstention_rate":1.0,"energy_coverage":1.0,"execution_failure_rate":0.0,"mean_gpu_joules":29.68834972866811,"queries":15,"route_id":"M17_granite_direct","success_rate":0.0,"task_type":"multi_hop"},{"abstention_rate":0.0,"energy_coverage":1.0,"execution_failure_rate":0.0,"mean_gpu_joules":229.2685602296707,"queries":15,"route_id":"M18_granite_grounded_verified","success_rate":0.0,"task_type":"multi_hop"},{"abstention_rate":0.0,"energy_coverage":1.0,"execution_failure_rate":0.0,"mean_gpu_joules":128.06404195571625,"queries":15,"route_id":"M19_peer_direct","success_rate":0.0,"task_type":"multi_hop"},{"abstention_rate":0.0,"energy_coverage":1.0,"execution_failure_rate":0.0,"mean_gpu_joules":149.99764749560364,"queries":15,"route_id":"M20_peer_grounded_verified","success_rate":0.0,"task_type":"multi_hop"},{"abstention_rate":1.0,"energy_coverage":1.0,"execution_failure_rate":0.0,"mean_gpu_joules":84.29464766533549,"queries":15,"route_id":"M21_upper_direct","success_rate":0.0,"task_type":"multi_hop"},{"abstention_rate":0.0,"energy_coverage":1.0,"execution_failure_rate":0.0,"mean_gpu_joules":45.634900789137724,"queries":15,"route_id":"A00_tiny_direct","success_rate":1.0,"task_type":"no_retrieval"},{"abstention_rate":0.3333333333333333,"energy_coverage":1.0,"execution_failure_rate":0.0,"mean_gpu_joules":154.6759957897348,"queries":15,"route_id":"A01_tiny_bm25","success_rate":0.0,"task_type":"no_retrieval"},{"abstention_rate":0.2,"energy_coverage":1.0,"execution_failure_rate":0.0,"mean_gpu_joules":153.97320271869114,"queries":15,"route_id":"A02_tiny_dense","success_rate":0.0,"task_type":"no_retrieval"},{"abstention_rate":0.0,"energy_coverage":1.0,"execution_failure_rate":0.0,"mean_gpu_joules":158.88843049687148,"queries":15,"route_id":"A03_tiny_hybrid","success_rate":0.0,"task_type":"no_retrieval"},{"abstention_rate":0.0,"energy_coverage":1.0,"execution_failure_rate":0.0,"mean_gpu_joules":254.28569858084074,"queries":15,"route_id":"A04_small_direct","success_rate":0.0,"task_type":"no_retrieval"},{"abstention_rate":0.06666666666666667,"energy_coverage":1.0,"execution_failure_rate":0.0,"mean_gpu_joules":162.69135161825997,"queries":15,"route_id":"A08_tiny_memory_flat","success_rate":0.0,"task_type":"no_retrieval"},{"abstention_rate":0.5333333333333333,"energy_coverage":1.0,"execution_failure_rate":0.0,"mean_gpu_joules":186.43881031094557,"queries":15,"route_id":"A09_tiny_memory_hier","success_rate":0.0,"task_type":"no_retrieval"},{"abstention_rate":0.5333333333333333,"energy_coverage":1.0,"execution_failure_rate":0.0,"mean_gpu_joules":186.67251617684505,"queries":15,"route_id":"A10_tiny_memory_graph","success_rate":0.0,"task_type":"no_retrieval"},{"abstention_rate":0.0,"energy_coverage":1.0,"execution_failure_rate":0.0,"mean_gpu_joules":257.62232564306015,"queries":15,"route_id":"A12_small_hybrid_both","success_rate":0.0,"task_type":"no_retrieval"},{"abstention_rate":1.0,"energy_coverage":1.0,"execution_failure_rate":0.0,"mean_gpu_joules":262.4360728696034,"queries":15,"route_id":"A13_small_hybrid_verified","success_rate":0.0,"task_type":"no_retrieval"},{"abstention_rate":1.0,"energy_coverage":1.0,"execution_failure_rate":0.0,"mean_gpu_joules":123.85202863796884,"queries":15,"route_id":"A14_upper_hybrid_verified","success_rate":0.0,"task_type":"no_retrieval"},{"abstention_rate":1.0,"energy_coverage":1.0,"execution_failure_rate":0.0,"mean_gpu_joules":183.32970611409084,"queries":15,"route_id":"M16_tiny_grounded_verified","success_rate":0.0,"task_type":"no_retrieval"},{"abstention_rate":0.3333333333333333,"energy_coverage":1.0,"execution_failure_rate":0.0,"mean_gpu_joules":93.78173879823439,"queries":15,"route_id":"M17_granite_direct","success_rate":0.6666666666666666,"task_type":"no_retrieval"},{"abstention_rate":1.0,"energy_coverage":1.0,"execution_failure_rate":0.0,"mean_gpu_joules":83.35159200911782,"queries":15,"route_id":"M18_granite_grounded_verified","success_rate":0.0,"task_type":"no_retrieval"},{"abstention_rate":0.0,"energy_coverage":1.0,"execution_failure_rate":0.0,"mean_gpu_joules":86.95747170179946,"queries":15,"route_id":"M19_peer_direct","success_rate":0.8666666666666667,"task_type":"no_retrieval"},{"abstention_rate":0.26666666666666666,"energy_coverage":1.0,"execution_failure_rate":0.0,"mean_gpu_joules":158.70260078436075,"queries":15,"route_id":"M20_peer_grounded_verified","success_rate":0.0,"task_type":"no_retrieval"},{"abstention_rate":0.9333333333333333,"energy_coverage":1.0,"execution_failure_rate":0.0,"mean_gpu_joules":94.11298314189028,"queries":15,"route_id":"M21_upper_direct","success_rate":0.06666666666666667,"task_type":"no_retrieval"},{"abstention_rate":0.0,"energy_coverage":1.0,"execution_failure_rate":0.0,"mean_gpu_joules":59.14058998567876,"queries":15,"route_id":"A00_tiny_direct","success_rate":0.0,"task_type":"temporal_update"},{"abstention_rate":0.0,"energy_coverage":1.0,"execution_failure_rate":0.0,"mean_gpu_joules":152.00529233535173,"queries":15,"route_id":"A01_tiny_bm25","success_rate":0.0,"task_type":"temporal_update"},{"abstention_rate":0.0,"energy_coverage":1.0,"execution_failure_rate":0.0,"mean_gpu_joules":152.76620240940474,"queries":15,"route_id":"A02_tiny_dense","success_rate":0.0,"task_type":"temporal_update"},{"abstention_rate":0.0,"energy_coverage":1.0,"execution_failure_rate":0.0,"mean_gpu_joules":135.95145083153753,"queries":15,"route_id":"A03_tiny_hybrid","success_rate":0.0,"task_type":"temporal_update"},{"abstention_rate":0.0,"energy_coverage":1.0,"execution_failure_rate":0.0,"mean_gpu_joules":257.46359032300774,"queries":15,"route_id":"A04_small_direct","success_rate":0.0,"task_type":"temporal_update"},{"abstention_rate":0.0,"energy_coverage":1.0,"execution_failure_rate":0.0,"mean_gpu_joules":156.52191694094913,"queries":15,"route_id":"A08_tiny_memory_flat","success_rate":0.0,"task_type":"temporal_update"},{"abstention_rate":0.0,"energy_coverage":1.0,"execution_failure_rate":0.0,"mean_gpu_joules":182.50543474427553,"queries":15,"route_id":"A09_tiny_memory_hier","success_rate":0.0,"task_type":"temporal_update"},{"abstention_rate":0.0,"energy_coverage":1.0,"execution_failure_rate":0.0,"mean_gpu_joules":182.63347030072984,"queries":15,"route_id":"A10_tiny_memory_graph","success_rate":0.0,"task_type":"temporal_update"},{"abstention_rate":0.0,"energy_coverage":1.0,"execution_failure_rate":0.0,"mean_gpu_joules":258.55547964368606,"queries":15,"route_id":"A12_small_hybrid_both","success_rate":0.0,"task_type":"temporal_update"},{"abstention_rate":1.0,"energy_coverage":1.0,"execution_failure_rate":0.0,"mean_gpu_joules":260.60581570501574,"queries":15,"route_id":"A13_small_hybrid_verified","success_rate":0.0,"task_type":"temporal_update"},{"abstention_rate":0.0,"energy_coverage":1.0,"execution_failure_rate":0.0,"mean_gpu_joules":230.3342467025479,"queries":15,"route_id":"A14_upper_hybrid_verified","success_rate":1.0,"task_type":"temporal_update"},{"abstention_rate":1.0,"energy_coverage":1.0,"execution_failure_rate":0.0,"mean_gpu_joules":199.3571134627093,"queries":15,"route_id":"M16_tiny_grounded_verified","success_rate":0.0,"task_type":"temporal_update"},{"abstention_rate":1.0,"energy_coverage":1.0,"execution_failure_rate":0.0,"mean_gpu_joules":29.593806896197403,"queries":15,"route_id":"M17_granite_direct","success_rate":0.0,"task_type":"temporal_update"},{"abstention_rate":0.0,"energy_coverage":1.0,"execution_failure_rate":0.0,"mean_gpu_joules":152.12717591265263,"queries":15,"route_id":"M18_granite_grounded_verified","success_rate":1.0,"task_type":"temporal_update"},{"abstention_rate":0.2,"energy_coverage":1.0,"execution_failure_rate":0.0,"mean_gpu_joules":112.08776628767605,"queries":15,"route_id":"M19_peer_direct","success_rate":0.0,"task_type":"temporal_update"},{"abstention_rate":0.06666666666666667,"energy_coverage":1.0,"execution_failure_rate":0.0,"mean_gpu_joules":129.41499234569517,"queries":15,"route_id":"M20_peer_grounded_verified","success_rate":0.9333333333333333,"task_type":"temporal_update"},{"abstention_rate":1.0,"energy_coverage":1.0,"execution_failure_rate":0.0,"mean_gpu_joules":83.74516136347418,"queries":15,"route_id":"M21_upper_direct","success_rate":0.0,"task_type":"temporal_update"}],"schema_version":1}
